CHANGELOG.txt
LICENSE.txt
MANIFEST.in
README.rst
setup.py
font_roboto/__init__.py
font_roboto.egg-info/PKG-INFO
font_roboto.egg-info/SOURCES.txt
font_roboto.egg-info/dependency_links.txt
font_roboto.egg-info/entry_points.txt
font_roboto.egg-info/not-zip-safe
font_roboto.egg-info/top_level.txt
font_roboto/files/LICENSE
font_roboto/files/Roboto-Black.ttf
font_roboto/files/Roboto-BlackItalic.ttf
font_roboto/files/Roboto-Bold.ttf
font_roboto/files/Roboto-BoldItalic.ttf
font_roboto/files/Roboto-Italic.ttf
font_roboto/files/Roboto-Light.ttf
font_roboto/files/Roboto-LightItalic.ttf
font_roboto/files/Roboto-Medium.ttf
font_roboto/files/Roboto-MediumItalic.ttf
font_roboto/files/Roboto-Regular.ttf
font_roboto/files/Roboto-Thin.ttf
font_roboto/files/Roboto-ThinItalic.ttf